{
  "cordova-plugin-whitelist": {
    "source": {
      "type": "registry",
      "id": "cordova-plugin-whitelist@1.3.3"
    },
    "is_top_level": true,
    "variables": {}
  },
  "cordova-plugin-splashscreen": {
    "source": {
      "type": "registry",
      "id": "cordova-plugin-splashscreen@5.0.2"
    },
    "is_top_level": true,
    "variables": {}
  },
  "cordova-plugin-background-audio": {
    "source": {
      "type": "registry",
      "id": "cordova-plugin-background-audio"
    },
    "is_top_level": true,
    "variables": {}
  },
  "cordova-plugin-crosswalk-webview-v2": {
    "source": {
      "type": "registry",
      "id": "cordova-plugin-crosswalk-webview-v2@2.4.3"
    },
    "is_top_level": true,
    "variables": {}
  }
}